alibabacloud_dlfnext20250310/__init__.py
alibabacloud_dlfnext20250310/client.py
alibabacloud_dlfnext20250310/models/__init__.py
alibabacloud_dlfnext20250310/models/_alter_catalog_request.py
alibabacloud_dlfnext20250310/models/_alter_catalog_response.py
alibabacloud_dlfnext20250310/models/_alter_catalog_response_body.py
alibabacloud_dlfnext20250310/models/_alter_database_request.py
alibabacloud_dlfnext20250310/models/_alter_database_response.py
alibabacloud_dlfnext20250310/models/_alter_database_response_body.py
alibabacloud_dlfnext20250310/models/_alter_receiver_request.py
alibabacloud_dlfnext20250310/models/_alter_receiver_response.py
alibabacloud_dlfnext20250310/models/_alter_share_receivers_request.py
alibabacloud_dlfnext20250310/models/_alter_share_receivers_response.py
alibabacloud_dlfnext20250310/models/_alter_share_request.py
alibabacloud_dlfnext20250310/models/_alter_share_resources_request.py
alibabacloud_dlfnext20250310/models/_alter_share_resources_response.py
alibabacloud_dlfnext20250310/models/_alter_share_response.py
alibabacloud_dlfnext20250310/models/_alter_table_request.py
alibabacloud_dlfnext20250310/models/_alter_table_response.py
alibabacloud_dlfnext20250310/models/_batch_grant_permissions_request.py
alibabacloud_dlfnext20250310/models/_batch_grant_permissions_response.py
alibabacloud_dlfnext20250310/models/_batch_grant_permissions_response_body.py
alibabacloud_dlfnext20250310/models/_batch_revoke_permissions_request.py
alibabacloud_dlfnext20250310/models/_batch_revoke_permissions_response.py
alibabacloud_dlfnext20250310/models/_batch_revoke_permissions_response_body.py
alibabacloud_dlfnext20250310/models/_catalog.py
alibabacloud_dlfnext20250310/models/_catalog_summary.py
alibabacloud_dlfnext20250310/models/_catalog_summary_trend.py
alibabacloud_dlfnext20250310/models/_create_catalog_request.py
alibabacloud_dlfnext20250310/models/_create_catalog_response.py
alibabacloud_dlfnext20250310/models/_create_database_request.py
alibabacloud_dlfnext20250310-3.5.0.dist-info/LICENSE
alibabacloud_dlfnext20250310-3.5.0.dist-info/METADATA
alibabacloud_dlfnext20250310-3.5.0.dist-info/WHEEL
alibabacloud_dlfnext20250310-3.5.0.dist-info/top_level.txt
alibabacloud_dlfnext20250310-3.5.0.dist-info/RECORD
